Workbook

Sheet Daily Reconciliation
A1: DAILY RECONCILIATION CHECKLIST
A2: Date: 2026-02-15
A4: Check # | B4: Reconciliation Item | C4: Formula/Check | D4: Expected Result | E4: Actual Result | F4: Variance | G4: Status | H4: Notes
A5: 1 | B5: Master Bank Account Balance | C5: =Accounts!B2 -> 0 | F5: =E5-D5 -> 0 | G5: =IF(ABS(F5)<0.01,"PASS","FAIL") -> PASS | H5: Sum of external bank accounts
A6: 2 | B6: User Bank Accounts Total | C6: =SUM(Accounts!B4:B20) -> 0 | F6: =E6-D6 -> 0 | G6: =IF(ABS(F6)<0.01,"PASS","FAIL") -> PASS | H6: Must equal distributed funds from Master Bank
A7: 3 | B7: Master Fund Account Balance | C7: =Accounts!B3 -> 0 | F7: =E7-D7 -> 0 | G7: =IF(ABS(F7)<0.01,"PASS","FAIL") -> PASS | H7: Sum of User Fund Accounts - Outstanding Loans
A8: 4 | B8: User Fund Accounts Total | C8: =SUM(Accounts!C4:C20) -> 0 | F8: =E8-D8 -> 0 | G8: =IF(ABS(F8)<0.01,"PASS","FAIL") -> PASS | H8: Sum of all user contributions + repayments
A9: 5 | B9: Total Outstanding Loans | C9: =SUM(Accounts!D4:D20) -> 0 | F9: =E9-D9 -> 0 | G9: =IF(ABS(F9)<0.01,"PASS","FAIL") -> PASS | H9: Sum of all active user loans
A10: 6 | B10: Fund Balance Check | C10: =D7 -> 0 | D10: =D8-D9 -> 0 | F10: =E10-D10 -> 0 | G10: =IF(ABS(F10)<0.01,"PASS","FAIL") -> PASS | H10: Master Fund = User Funds - Loans
A11: 7 | B11: Cash Flow Balance | C11: =D5 -> 0 | D11: =D6+D7 -> 0 | F11: =E11-D11 -> 0 | G11: =IF(ABS(F11)<0.01,"PASS","FAIL") -> PASS | H11: Master Bank = User Banks + Master Fund

Sheet Accounts
A1: ACCOUNT BALANCES & TRACKING
A3: MASTER ACCOUNTS
A4: Master Bank Account | B4: 0
A5: Master Fund Account | B5: 0
A7: USER ACCOUNTS
A8: User ID | B8: User Bank Account | C8: User Fund Account | D8: Outstanding Loans | E8: Available to Borrow
A9: USER001 | B9: 0 | C9: 0 | D9: 0 | E9: =C9-D9 -> 0
A10: USER002 | B10: 0 | C10: 0 | D10: 0 | E10: =C10-D10 -> 0
A11: USER003 | B11: 0 | C11: 0 | D11: 0 | E11: =C11-D11 -> 0
A12: USER004 | B12: 0 | C12: 0 | D12: 0 | E12: =C12-D12 -> 0
A13: USER005 | B13: 0 | C13: 0 | D13: 0 | E13: =C13-D13 -> 0
A14: USER006 | B14: 0 | C14: 0 | D14: 0 | E14: =C14-D14 -> 0
A15: USER007 | B15: 0 | C15: 0 | D15: 0 | E15: =C15-D15 -> 0
A16: USER008 | B16: 0 | C16: 0 | D16: 0 | E16: =C16-D16 -> 0
A17: USER009 | B17: 0 | C17: 0 | D17: 0 | E17: =C17-D17 -> 0
A18: USER010 | B18: 0 | C18: 0 | D18: 0 | E18: =C18-D18 -> 0

Sheet Transaction Log
A1: TRANSACTION LOG
A3: Date | B3: Time | C3: Transaction ID | D3: Type | E3: From Account | F3: To Account | G3: Amount | H3: User ID | I3: Reference | J3: Status | K3: Notes

Sheet External Bank Import
A1: EXTERNAL BANK ACCOUNT IMPORTS
A3: Import tracking and duplicate detection
A5: Import Date | B5: Bank Account | C5: Transaction Date | D5: External Ref ID | E5: Amount | F5: Description | G5: Imported to Master | H5: Duplicate Flag | I5: Notes

Sheet Loan Tracking
A1: USER LOAN ACCOUNTS
A3: Loan ID | B3: User ID | C3: Origination Date | D3: Original Amount | E3: Interest Rate | F3: Term (months) | G3: Monthly Payment | H3: Total Paid | I3: Outstanding Balance | J3: Status | K3: Next Payment Date

Sheet Balance Equations
A1: CRITICAL BALANCE EQUATIONS
A3: These mathematical relationships MUST always hold true:
A5: Equation 1 | B5: Master Bank Account | C5: = | D5: Sum of External Bank Accounts | E5: =Accounts!B4 -> 0 | G5: See External Bank Import sheet
A7: Equation 2 | B7: Master Bank Account | C7: = | D7: Sum of User Bank Accounts + Master Fund Account | E7: =Accounts!B4 -> 0 | F7: = | G7: =SUM(Accounts!B9:B18)+Accounts!B5 -> 0
A9: Equation 3 | B9: Master Fund Account | C9: = | D9: Sum of User Fund Accounts - Total Outstanding Loans | E9: =Accounts!B5 -> 0 | F9: = | G9: =SUM(Accounts!C9:C18)-SUM(Accounts!D9:D18) -> 0
A11: Equation 4 | B11: User Fund Account (each) | C11: = | D11: Contributions + Loan Repayments (cumulative) | G11: Track in Transaction Log
A13: Equation 5 | B13: Outstanding Loan Balance | C13: = | D13: Original Amount - Total Repayments | G13: Track in Loan Tracking sheet

Sheet Exception Handling
A1: EXCEPTION HANDLING WORKFLOW
A3: Exception Type | B3: Detection Method | C3: Severity | D3: Resolution Steps | E3: Responsible Party | F3: SLA (hours)
A4: Duplicate Import | B4: External Ref ID matches existing | C4: Medium | D4: 1. Flag transaction 2. Investigate source 3. Remove duplicate 4. Document | E4: Accounting Team | F4: 4
A5: Balance Mismatch | B5: Daily reconciliation formulas | C5: High | D5: 1. Identify variance source 2. Review transaction log 3. Trace to account 4. Correct entry 5. Re-reconcile | E5: Accounting Manager | F5: 2
A6: Negative Balance | B6: Account balance < 0 | C6: High | D6: 1. Halt new transactions 2. Review transaction history 3. Identify error 4. Reverse if needed 5. Restore balance | E6: Accounting Manager | F6: 2
A7: Loan Payment Mismatch | B7: Payment ≠ scheduled amount | C7: Medium | D7: 1. Check payment record 2. Contact user 3. Apply correct amount 4. Adjust schedule if needed | E7: Loan Officer | F7: 24
A8: Missing Transaction | B8: Bank statement vs Master Bank | C8: High | D8: 1. Compare statements 2. Locate transaction 3. Import/create entry 4. Verify reconciliation | E8: Accounting Team | F8: 4
A9: Fund Account Negative | B9: User Fund Account < 0 | C9: Critical | D9: 1. Freeze account 2. Review all transactions 3. Identify cause 4. Reverse error 5. Notify user | E9: Accounting Manager | F9: 1

Sheet Audit Trail Requirements
A1: AUDIT TRAIL REQUIREMENTS
A3: Required documentation for each transaction type:
A5: Transaction Type | B5: Required Fields | C5: Supporting Documentation | D5: Retention Period | E5: Review Frequency
A6: External Bank Import | B6: Date, Time, Bank Account, Amount, External Ref ID, Description | C6: Bank statement, Import file, Duplicate check log | D6: 7 years | E6: Daily
A7: Master Bank → User Bank | B7: Date, Time, Amount, User ID, Distribution basis, Approval | C7: Distribution schedule, Manager approval | D7: 7 years | E7: Monthly
A8: User Bank → User Fund | B8: Date, Time, Amount, User ID, Transaction type (contribution/repayment), Reference | C8: Payment receipt, User confirmation | D8: 7 years | E8: Monthly
A9: Loan Disbursement | B9: Date, Time, Loan ID, User ID, Amount, Terms, Approval | C9: Loan agreement, Credit approval, User acknowledgment | D9: 7 years + loan term | E9: Per transaction
A10: Loan Repayment | B10: Date, Time, Loan ID, User ID, Amount, Principal, Interest, Balance | C10: Payment receipt, Amortization schedule | D10: 7 years + loan term | E10: Monthly
A11: Account Adjustments | B11: Date, Time, Account, Amount, Reason, Approver, Before/After balance | C11: Adjustment memo, Manager approval, Supporting docs | D11: 7 years | E11: Per transaction
